README.md
setup.cfg
setup.py
SnakeGame.egg-info/PKG-INFO
SnakeGame.egg-info/SOURCES.txt
SnakeGame.egg-info/dependency_links.txt
SnakeGame.egg-info/entry_points.txt
SnakeGame.egg-info/top_level.txt
SnakeGame.egg-info/zip-safe
snakegame/__init__.py
snakegame/config.py
snakegame/engine.py
snakegame/entities/__init__.py
snakegame/entities/drawable.py
snakegame/entities/entity.py
snakegame/entities/fruit.py
snakegame/entities/moveable.py
snakegame/entities/snake.py
snakegame/gamestates/__init__.py
snakegame/gamestates/ended.py
snakegame/gamestates/paused.py
snakegame/gamestates/playing.py
snakegame/utilities/__init__.py
snakegame/utilities/vector.py