Metadata-Version: 1.2
Name: SnakeGame
Version: 1.0.0.0
Summary: Snake game
Home-page: https://github.com/vedard/SnakeGame/
Author: Vincent Bédard
Author-email: UNKNOWN
License: MIT
Keywords: snake game
Platform: UNKNOWN
Requires-Python: >=3.6
